swh/digestmap.cpython-311-x86_64-linux-musl.so
swh/digestmap.pyi
swh/digestmap/.gitignore
swh/digestmap/Cargo.toml
swh/digestmap/install_wheel_build_deps.sh
swh/digestmap/src/lib.rs
swh/digestmap/tests/test_digestmap.py
swh/digestmap/tests/assets/README.md
swh/digestmap/tests/assets/sha1.bin
swh/digestmap/tests/assets/sha1_git.bin
swh/digestmap/tests/assets/sha1_git.vfunc
swh_digestmap.libs/libgcc_s-0cd532bd.so.1
swh_digestmap-0.2.1.dist-info/METADATA
swh_digestmap-0.2.1.dist-info/WHEEL
swh_digestmap-0.2.1.dist-info/entry_points.txt
swh_digestmap-0.2.1.dist-info/top_level.txt
swh_digestmap-0.2.1.dist-info/RECORD
swh_digestmap-0.2.1.dist-info/licenses/AUTHORS
swh_digestmap-0.2.1.dist-info/licenses/LICENSE
