Metadata-Version: 2.4
Name: swh.digestmap
Version: 0.2.1
Author-email: Software Heritage developers <swh-devel@inria.fr>
License-Expression: GPL-3.0
Project-URL: Homepage, https://softwareheritage.org/
Project-URL: Documentation, https://docs.softwareheritage.org/devel/swh-digestmap/
Project-URL: Repository, https://gitlab.softwareheritage.org/swh/devel/swh-digestmap
Classifier: Programming Language :: Rust
Classifier: Intended Audience :: Developers
Classifier: Development Status :: 4 - Beta
Requires-Python: >=3.9
License-File: LICENSE
License-File: AUTHORS
Requires-Dist: swh.model>=8.0.0
Provides-Extra: testing
Requires-Dist: pytest; extra == "testing"
Dynamic: license-file
